{
    "forex": {
        "AUDCAD": {
            "signal": "SELL",
            "price": 0.91371,
            "close": 24.913710000000002,
            "accuracy": 73.00000000000084,
            "date": "2025-11-04 12:30:00"
        },
        "AUDCHF": {
            "signal": "BUY",
            "price": 0.52464,
            "close": 24.52464,
            "accuracy": 24.000000000001794,
            "date": "2025-11-04 17:30:00"
        },
        "AUDJPY": {
            "signal": "SELL",
            "price": 99.656,
            "close": 123.656,
            "accuracy": 17600.000000000193,
            "date": "2025-11-04 12:30:00"
        },
        "AUDSEK": {
            "signal": "BUY",
            "price": 6.20333,
            "close": 30.20333,
            "accuracy": 208.9999999999925,
            "date": "2025-11-04 17:30:00"
        },
        "AUDSGD": {
            "signal": "SELL",
            "price": 0.84778,
            "close": 24.84778,
            "accuracy": 85.99999999999719,
            "date": "2025-11-04 12:30:00"
        },
        "AUDUSD": {
            "signal": "SELL",
            "price": 0.64866,
            "close": 24.64866,
            "accuracy": 39.00000000000014,
            "date": "2025-11-04 17:00:00"
        },
        "CADJPY": {
            "signal": "SELL",
            "price": 109.043,
            "close": 133.043,
            "accuracy": 9500.000000001306,
            "date": "2025-11-04 12:30:00"
        },
        "CHFHUF": {
            "signal": "BUY",
            "price": 417.897,
            "close": 441.897,
            "accuracy": 4399.999999998272,
            "date": "2025-11-04 17:00:00"
        },
        "CHFJPY": {
            "signal": "SELL",
            "price": 189.481,
            "close": 213.481,
            "accuracy": 1300.000000000523,
            "date": "2025-11-04 17:30:00"
        },
        "CHFNOK": {
            "signal": "BUY",
            "price": 12.5942,
            "close": 36.5942,
            "accuracy": 296.9999999999473,
            "date": "2025-11-04 12:30:00"
        },
        "CHFPLN": {
            "signal": "SELL",
            "price": 4.57895,
            "close": 28.57895,
            "accuracy": 77.99999999997809,
            "date": "2025-11-04 17:30:00"
        },
        "CHFSEK": {
            "signal": "BUY",
            "price": 11.77669,
            "close": 35.77669,
            "accuracy": 112.00000000002318,
            "date": "2025-11-04 12:30:00"
        },
        "CHFSGD": {
            "signal": "SELL",
            "price": 1.61407,
            "close": 25.614069999999998,
            "accuracy": 28.000000000005794,
            "date": "2025-11-04 17:30:00"
        },
        "EURAUD": {
            "signal": "SELL",
            "price": 1.76735,
            "close": 25.76735,
            "accuracy": 41.000000000002146,
            "date": "2025-11-04 17:30:00"
        },
        "EURCAD": {
            "signal": "SELL",
            "price": 1.61799,
            "close": 25.61799,
            "accuracy": 52.999999999991935,
            "date": "2025-11-04 12:30:00"
        },
        "EURCNH": {
            "signal": "SELL",
            "price": 8.18448,
            "close": 32.18448,
            "accuracy": 634.9999999999411,
            "date": "2025-11-04 17:00:00"
        },
        "EURHKD": {
            "signal": "SELL",
            "price": 8.91912,
            "close": 32.91912,
            "accuracy": 58.00000000011351,
            "date": "2025-11-04 17:30:00"
        },
        "EURHUF": {
            "signal": "BUY",
            "price": 388.371,
            "close": 412.371,
            "accuracy": 13099.999999997179,
            "date": "2025-11-04 17:00:00"
        },
        "EURILS": {
            "signal": "SELL",
            "price": 4.06192,
            "close": 28.06192,
            "accuracy": 682.000000000027,
            "date": "2023-09-04 21:00:00"
        },
        "EURJPY": {
            "signal": "SELL",
            "price": 176.134,
            "close": 200.134,
            "accuracy": 7599.99999999934,
            "date": "2025-11-04 17:00:00"
        },
        "EURNOK": {
            "signal": "BUY",
            "price": 11.717459999999999,
            "close": 35.71746,
            "accuracy": 122.99999999996201,
            "date": "2025-11-04 12:30:00"
        },
        "EURNZD": {
            "signal": "SELL",
            "price": 2.02671,
            "close": 26.02671,
            "accuracy": 76.99999999997154,
            "date": "2025-11-04 17:30:00"
        },
        "EURRUB": {
            "signal": "SELL",
            "price": 92.091,
            "close": 116.091,
            "accuracy": 5900.0000000011705,
            "date": "2025-11-04 12:30:00"
        },
        "EURSGD": {
            "signal": "SELL",
            "price": 1.50114,
            "close": 25.50114,
            "accuracy": 71.00000000002105,
            "date": "2025-11-04 12:30:00"
        },
        "EURTRY": {
            "signal": "SELL",
            "price": 48.42649,
            "close": 72.42649,
            "accuracy": 2193.0000000004666,
            "date": "2025-11-04 12:30:00"
        },
        "GBPCAD": {
            "signal": "SELL",
            "price": 1.83662,
            "close": 25.83662,
            "accuracy": 119.00000000000243,
            "date": "2025-11-04 17:00:00"
        },
        "GBPHKD": {
            "signal": "BUY",
            "price": 10.5327,
            "close": 34.5327,
            "accuracy": 40.00000000008441,
            "date": "2025-07-25 21:00:00"
        },
        "GBPJPY": {
            "signal": "SELL",
            "price": 200.137,
            "close": 224.137,
            "accuracy": 8299.99999999984,
            "date": "2025-11-04 17:00:00"
        },
        "GBPSGD": {
            "signal": "SELL",
            "price": 1.70466,
            "close": 25.70466,
            "accuracy": 90.99999999997442,
            "date": "2025-11-04 17:00:00"
        },
        "GBPTRY": {
            "signal": "SELL",
            "price": 54.91653,
            "close": 78.91653,
            "accuracy": 5580.000000000495,
            "date": "2025-11-04 17:00:00"
        },
        "GBPUSD": {
            "signal": "SELL",
            "price": 1.3041800000000001,
            "close": 25.30418,
            "accuracy": 140.00000000000676,
            "date": "2025-11-04 17:00:00"
        },
        "HKDJPY": {
            "signal": "SELL",
            "price": 19.73,
            "close": 43.730000000000004,
            "accuracy": 1099.9999999999231,
            "date": "2025-11-04 12:30:00"
        },
        "NOKJPY": {
            "signal": "SELL",
            "price": 15.042,
            "close": 39.042,
            "accuracy": 2299.9999999999686,
            "date": "2025-11-04 12:30:00"
        },
        "NZDCAD": {
            "signal": "SELL",
            "price": 0.79636,
            "close": 24.79636,
            "accuracy": 43.99999999999959,
            "date": "2025-11-04 12:30:00"
        },
        "NZDDKK": {
            "signal": "BUY",
            "price": 3.6782500000000002,
            "close": 27.67825,
            "accuracy": 124.00000000001297,
            "date": "2025-11-04 17:30:00"
        },
        "NZDJPY": {
            "signal": "SELL",
            "price": 86.869,
            "close": 110.869,
            "accuracy": 13199.999999999078,
            "date": "2025-11-04 12:30:00"
        },
        "NZDSGD": {
            "signal": "SELL",
            "price": 0.73904,
            "close": 24.73904,
            "accuracy": 55.00000000000504,
            "date": "2025-11-04 12:30:00"
        },
        "NZDUSD": {
            "signal": "SELL",
            "price": 0.56609,
            "close": 24.56609,
            "accuracy": 43.00000000000414,
            "date": "2025-11-04 12:30:00"
        },
        "SEKJPY": {
            "signal": "SELL",
            "price": 16.089,
            "close": 40.089,
            "accuracy": 2400.000000000091,
            "date": "2025-11-04 12:30:00"
        },
        "SEKNOK": {
            "signal": "SELL",
            "price": 0.97647,
            "close": 24.97647,
            "accuracy": 397.0000000000029,
            "date": "2023-07-10 09:30:00"
        },
        "SGDJPY": {
            "signal": "SELL",
            "price": 117.507,
            "close": 141.507,
            "accuracy": 7999.999999999829,
            "date": "2025-11-04 12:30:00"
        },
        "TRYJPY": {
            "signal": "BUY",
            "price": 3.614,
            "close": 27.614,
            "accuracy": 99.99999999998897,
            "date": "2025-11-04 17:00:00"
        },
        "USDCHF": {
            "signal": "BUY",
            "price": 0.80769,
            "close": 24.80769,
            "accuracy": 26.000000000003794,
            "date": "2025-11-04 12:30:00"
        },
        "USDCNH": {
            "signal": "BUY",
            "price": 7.13135,
            "close": 31.13135,
            "accuracy": 143.99999999996638,
            "date": "2025-11-04 17:30:00"
        },
        "USDCZK": {
            "signal": "BUY",
            "price": 21.16318,
            "close": 45.16318,
            "accuracy": 380.00000000018014,
            "date": "2025-11-04 17:30:00"
        },
        "USDDKK": {
            "signal": "BUY",
            "price": 6.4943100000000005,
            "close": 30.49431,
            "accuracy": 619.9999999999761,
            "date": "2025-11-04 17:00:00"
        },
        "USDGEL": {
            "signal": "SELL",
            "price": 2.6644,
            "close": 26.6644,
            "accuracy": 879.9999999999918,
            "date": "2019-03-04 23:00:00"
        },
        "USDHUF": {
            "signal": "BUY",
            "price": 337.793,
            "close": 361.793,
            "accuracy": 51999.999999998174,
            "date": "2025-11-04 17:00:00"
        },
        "USDILS": {
            "signal": "BUY",
            "price": 3.26627,
            "close": 27.26627,
            "accuracy": 64.99999999998174,
            "date": "2025-11-04 17:00:00"
        },
        "USDJPY": {
            "signal": "SELL",
            "price": 153.403,
            "close": 177.403,
            "accuracy": 8299.99999999984,
            "date": "2025-11-04 12:30:00"
        },
        "USDMXN": {
            "signal": "BUY",
            "price": 18.6188,
            "close": 42.6188,
            "accuracy": 740.0000000000516,
            "date": "2025-11-04 12:30:00"
        },
        "USDNOK": {
            "signal": "BUY",
            "price": 10.17981,
            "close": 34.17981,
            "accuracy": 664.0000000000867,
            "date": "2025-11-04 12:30:00"
        },
        "USDPLN": {
            "signal": "BUY",
            "price": 3.70252,
            "close": 27.70252,
            "accuracy": 387.000000000004,
            "date": "2025-11-04 17:00:00"
        },
        "USDRMB": {
            "signal": "BUY",
            "price": 7.13135,
            "close": 31.13135,
            "accuracy": 143.99999999996638,
            "date": "2025-11-04 17:30:00"
        },
        "USDSEK": {
            "signal": "BUY",
            "price": 9.51877,
            "close": 33.51877,
            "accuracy": 590.000000000046,
            "date": "2025-11-04 12:30:00"
        },
        "USDTHB": {
            "signal": "BUY",
            "price": 32.51,
            "close": 56.51,
            "accuracy": 4700.000000000415,
            "date": "2025-11-04 17:00:00"
        },
        "ZARJPY": {
            "signal": "SELL",
            "price": 8.579,
            "close": 32.579,
            "accuracy": 799.9999999999118,
            "date": "2025-11-04 12:30:00"
        },
        "GBPCZK": {
            "signal": "BUY",
            "price": 27.68477,
            "close": 51.68477,
            "accuracy": 88.99999999982809,
            "date": "2025-11-04 17:30:00"
        },
        "GBPPLN": {
            "signal": "BUY",
            "price": 4.83632,
            "close": 28.83632,
            "accuracy": 60.000000000037794,
            "date": "2025-11-04 14:30:00"
        },
        "NOKSEK": {
            "signal": "BUY",
            "price": 0.9346,
            "close": 24.9346,
            "accuracy": 28.000000000005794,
            "date": "2025-11-04 14:30:00"
        },
        "NZDSEK": {
            "signal": "BUY",
            "price": 5.41269,
            "close": 29.412689999999998,
            "accuracy": 213.99999999998084,
            "date": "2025-11-04 17:30:00"
        },
        "EURRUR": {
            "signal": "SELL",
            "price": 91.928,
            "close": 115.928,
            "accuracy": 7800.000000000295,
            "date": "2025-11-04 15:00:00"
        },
        "CADCHF": {
            "signal": "BUY",
            "price": 0.57449,
            "close": 24.57449,
            "accuracy": 23.000000000006345,
            "date": "2025-11-04 14:30:00"
        },
        "DKKSEK": {
            "signal": "BUY",
            "price": 1.47035,
            "close": 25.47035,
            "accuracy": 89.00000000000573,
            "date": "2025-11-04 14:30:00"
        },
        "EURCZK": {
            "signal": "BUY",
            "price": 24.36638,
            "close": 48.36638,
            "accuracy": 462.9999999998801,
            "date": "2025-11-04 17:30:00"
        },
        "EURSEK": {
            "signal": "BUY",
            "price": 10.97672,
            "close": 34.97672,
            "accuracy": 638.0000000000052,
            "date": "2025-11-04 14:30:00"
        },
        "GBPAUD": {
            "signal": "SELL",
            "price": 2.00752,
            "close": 26.00752,
            "accuracy": 62.00000000000649,
            "date": "2025-11-04 17:30:00"
        },
        "GBPHUF": {
            "signal": "BUY",
            "price": 440.704,
            "close": 464.704,
            "accuracy": 2400.000000000091,
            "date": "2025-11-04 17:00:00"
        },
        "GBPNOK": {
            "signal": "BUY",
            "price": 13.32775,
            "close": 37.32775,
            "accuracy": 132.99999999993872,
            "date": "2025-11-04 14:30:00"
        },
        "GBPSEK": {
            "signal": "BUY",
            "price": 12.46777,
            "close": 36.46777,
            "accuracy": 940.9999999999029,
            "date": "2025-11-04 14:30:00"
        },
        "USDHKD": {
            "signal": "SELL",
            "price": 7.773,
            "close": 31.773,
            "accuracy": 22.000000000055305,
            "date": "2025-11-04 14:30:00"
        },
        "EURUSD": {
            "signal": "SELL",
            "price": 1.14773,
            "close": 25.14773,
            "accuracy": 115.99999999998278,
            "date": "2025-11-04 17:00:00"
        },
        "EURZAR": {
            "signal": "BUY",
            "price": 20.04753,
            "close": 44.047529999999995,
            "accuracy": 400.0000000001335,
            "date": "2025-11-04 15:00:00"
        },
        "GBPDKK": {
            "signal": "BUY",
            "price": 8.47458,
            "close": 32.47458,
            "accuracy": 25.000000000119368,
            "date": "2025-11-04 15:00:00"
        },
        "GBPZAR": {
            "signal": "BUY",
            "price": 22.78069,
            "close": 46.78069,
            "accuracy": 2049.999999999841,
            "date": "2025-11-04 15:00:00"
        },
        "SGDHKD": {
            "signal": "SELL",
            "price": 5.94565,
            "close": 29.94565,
            "accuracy": 289.00000000007253,
            "date": "2025-11-04 17:00:00"
        },
        "USDSGD": {
            "signal": "BUY",
            "price": 1.30652,
            "close": 25.30652,
            "accuracy": 71.99999999998319,
            "date": "2025-11-04 17:00:00"
        },
        "USDZAR": {
            "signal": "BUY",
            "price": 17.44509,
            "close": 41.44509,
            "accuracy": 1520.00000000001,
            "date": "2025-11-04 15:00:00"
        },
        "EURDKK": {
            "signal": "SELL",
            "price": 7.46426,
            "close": 31.46426,
            "accuracy": 25.999999999992692,
            "date": "2025-11-04 17:00:00"
        },
        "EURMXN": {
            "signal": "SELL",
            "price": 21.35099,
            "close": 45.350989999999996,
            "accuracy": 359.9999999998715,
            "date": "2025-11-04 17:30:00"
        },
        "GBPMXN": {
            "signal": "SELL",
            "price": 24.24687,
            "close": 48.24687,
            "accuracy": 215.99999999999395,
            "date": "2025-11-04 17:30:00"
        },
        "GBPNZD": {
            "signal": "SELL",
            "price": 2.30213,
            "close": 26.30213,
            "accuracy": 126.00000000002608,
            "date": "2025-11-04 17:30:00"
        },
        "USDCAD": {
            "signal": "BUY",
            "price": 1.40781,
            "close": 25.40781,
            "accuracy": 29.000000000012346,
            "date": "2025-11-04 17:00:00"
        },
        "CHFDKK": {
            "signal": "SELL",
            "price": 8.02875,
            "close": 32.02875,
            "accuracy": 103.00000000000863,
            "date": "2025-11-04 17:30:00"
        },
        "NZDCHF": {
            "signal": "BUY",
            "price": 0.45767,
            "close": 24.45767,
            "accuracy": 26.999999999999243,
            "date": "2025-11-04 17:30:00"
        },
        "USDRUB": {
            "signal": "SELL",
            "price": 80.033,
            "close": 104.033,
            "accuracy": 21999.999999999884,
            "date": "2025-11-04 17:30:00"
        }
    },
    "index": {
        "AUS200": {
            "signal": "BUY",
            "price": 8796.8,
            "close": 8820.8,
            "accuracy": 3199999.9999999995,
            "date": "2025-11-04 17:30:00"
        },
        "FCHI40": {
            "signal": "SELL",
            "price": 6659.4,
            "close": 6683.4,
            "accuracy": 449999.99999999994,
            "date": "2022-12-09 23:00:00"
        },
        "SP500m": {
            "signal": "SELL",
            "price": 3957.8,
            "close": 3981.8,
            "accuracy": 99999.99999999999,
            "date": "2022-12-09 23:00:00"
        },
        "SPN35": {
            "signal": "BUY",
            "price": 7915.0,
            "close": 7939.0,
            "accuracy": 99999.99999999999,
            "date": "2022-09-19 14:30:00"
        },
        "STOX50": {
            "signal": "SELL",
            "price": 3934.8,
            "close": 3958.8,
            "accuracy": 300000.0,
            "date": "2022-12-09 23:00:00"
        },
        "EUSTX50": {
            "signal": "BUY",
            "price": 5636.2,
            "close": 5660.2,
            "accuracy": 2200000.0,
            "date": "2025-11-04 17:30:00"
        },
        "FRA40": {
            "signal": "BUY",
            "price": 8030.1,
            "close": 8054.1,
            "accuracy": 1849999.9999999998,
            "date": "2025-11-04 17:30:00"
        },
        "HK50": {
            "signal": "SELL",
            "price": 25704.5,
            "close": 25728.5,
            "accuracy": 2350000.0,
            "date": "2025-11-04 12:30:00"
        },
        "JPN225": {
            "signal": "BUY",
            "price": 51194.0,
            "close": 51218.0,
            "accuracy": 23199999.999999996,
            "date": "2025-11-04 17:30:00"
        },
        "RVI.I": {
            "signal": "BUY",
            "price": 34.09,
            "close": 58.09,
            "accuracy": 65999.99999999965,
            "date": "2021-12-02 18:00:00"
        },
        "US500": {
            "signal": "BUY",
            "price": 6767.0,
            "close": 6791.0,
            "accuracy": 2230000.000000018,
            "date": "2025-11-04 17:30:00"
        },
        "US30M": {
            "signal": "BUY",
            "price": 47036.0,
            "close": 47060.0,
            "accuracy": 199999.99999999997,
            "date": "2025-11-04 13:00:00"
        },
        "US500M": {
            "signal": "BUY",
            "price": 6771.2,
            "close": 6795.2,
            "accuracy": 2230000.000000018,
            "date": "2025-11-04 17:30:00"
        },
        "USTECH100M": {
            "signal": "BUY",
            "price": 25559.8,
            "close": 25583.8,
            "accuracy": 12409999.999999853,
            "date": "2025-11-04 17:30:00"
        },
        "GER30M": {
            "signal": "BUY",
            "price": 23847.2,
            "close": 23871.2,
            "accuracy": 6799999.999999999,
            "date": "2025-11-04 17:30:00"
        },
        "DE40": {
            "signal": "BUY",
            "price": 23834.8,
            "close": 23858.8,
            "accuracy": 6899999.999999999,
            "date": "2025-11-04 17:30:00"
        },
        "US30": {
            "signal": "SELL",
            "price": 46869.2,
            "close": 46893.2,
            "accuracy": 5650000.0,
            "date": "2025-11-04 12:30:00"
        },
        "USTEC": {
            "signal": "BUY",
            "price": 25534.2,
            "close": 25558.2,
            "accuracy": 12440000.000000145,
            "date": "2025-11-04 17:30:00"
        },
        "CHINA50": {
            "signal": "SELL",
            "price": 15215.75,
            "close": 15239.75,
            "accuracy": 1100000.0,
            "date": "2025-11-04 12:30:00"
        },
        "CHINAH": {
            "signal": "SELL",
            "price": 9102.6,
            "close": 9126.6,
            "accuracy": 199999.99999999997,
            "date": "2025-11-04 12:30:00"
        },
        "IT40": {
            "signal": "SELL",
            "price": 42567.0,
            "close": 42591.0,
            "accuracy": 4300000.0,
            "date": "2025-11-04 12:30:00"
        },
        "NETH25": {
            "signal": "BUY",
            "price": 965.79,
            "close": 989.79,
            "accuracy": 270999.99999999226,
            "date": "2025-11-04 17:30:00"
        },
        "NOR25": {
            "signal": "BUY",
            "price": 1519.09,
            "close": 1543.09,
            "accuracy": 45000.00000000454,
            "date": "2025-11-04 16:30:00"
        },
        "SE30": {
            "signal": "SELL",
            "price": 2711.28,
            "close": 2735.28,
            "accuracy": 218000.00000002907,
            "date": "2025-11-04 12:30:00"
        },
        "SWI20": {
            "signal": "BUY",
            "price": 12213.45,
            "close": 12237.45,
            "accuracy": 3449999.9999999995,
            "date": "2025-11-04 17:30:00"
        },
        "US2000": {
            "signal": "SELL",
            "price": 2426.77,
            "close": 2450.77,
            "accuracy": 300000.0,
            "date": "2025-11-04 12:30:00"
        },
        "MIDDE50": {
            "signal": "BUY",
            "price": 29442.0,
            "close": 29466.0,
            "accuracy": 170000.00000007276,
            "date": "2025-11-04 17:00:00"
        },
        "TECHDE30": {
            "signal": "BUY",
            "price": 3593.7,
            "close": 3617.7,
            "accuracy": 650000.0,
            "date": "2025-11-04 17:30:00"
        },
        "SA40": {
            "signal": "BUY",
            "price": 99568.1,
            "close": 99592.1,
            "accuracy": 17980000.00000029,
            "date": "2025-11-04 17:30:00"
        }
    }
}